deskapi/__init__.py
deskapi/__main__.py
deskapi/config_manager.py
deskapi/convenience_methods.py
deskapi/franka_desk_api.py
deskapi/desk_api_cfg/config.yaml
deskapi/desk_api_cfg/robot.yaml
deskapi/desk_api_cfg/api_cfg/api_cfg.yaml
deskapi/desk_api_cfg/api_cfg/methods.yaml
franka_deskapi-1.0.0.dist-info/licenses/LICENSE
franka_deskapi-1.0.0.dist-info/METADATA
franka_deskapi-1.0.0.dist-info/WHEEL
franka_deskapi-1.0.0.dist-info/entry_points.txt
franka_deskapi-1.0.0.dist-info/top_level.txt
franka_deskapi-1.0.0.dist-info/RECORD
