Metadata-Version: 2.4
Name: franka-deskapi
Version: 1.0.0
Summary: Franka Desk API client library
Author-email: "Plug and Play Robotics (Suzhou) Co., Ltd." <chengyk@pnprobotics.com>
License: MPL-2.0
Project-URL: Homepage, https://www.pnprobotics.com
Project-URL: Documentation, https://docs.pnprobotics.com/franka-deskapi
Project-URL: Source, https://github.com/chengyk-pnprobotics/FrankaDeskApi
Project-URL: Tracker, https://github.com/chengyk-pnprobotics/FrankaDeskApi/issues
Project-URL: Download, https://pypi.org/project/franka-deskapi/
Keywords: franka,robotics,api,deskapi
Classifier: Development Status :: 4 - Beta
Classifier: Intended Audience :: Developers
Classifier: License :: OSI Approved :: Mozilla Public License 2.0 (MPL 2.0)
Classifier: Programming Language :: Python :: 3
Classifier: Programming Language :: Python :: 3.7
Classifier: Programming Language :: Python :: 3.8
Classifier: Programming Language :: Python :: 3.9
Classifier: Programming Language :: Python :: 3.10
Classifier: Programming Language :: Python :: 3.11
Classifier: Programming Language :: Python :: 3.12
Requires-Python: >=3.7
License-File: LICENSE
Requires-Dist: pyyaml>=5.4.1
Requires-Dist: setuptools>=61.0
Dynamic: license-file
